glia/__init__.py
glia/_cli.py
glia/_glia.py
glia/_hash.py
glia/assets.py
glia/exceptions.py
glia/library.py
glia/resolution.py
tests/__init__.py
tests/test_cli.py
tests/test_glia_runnable.py
nrn_glia-0.5.1.dist-info/LICENSE
nrn_glia-0.5.1.dist-info/METADATA
nrn_glia-0.5.1.dist-info/WHEEL
nrn_glia-0.5.1.dist-info/entry_points.txt
nrn_glia-0.5.1.dist-info/top_level.txt
nrn_glia-0.5.1.dist-info/RECORD
