Metadata-Version: 2.1
Name: nrn-glia
Version: 0.5.1
Summary: Package manager for NEURON
Home-page: https://github.com/dbbs-lab/glia
Author: Robin De Schepper
Author-email: robingilbert.deschepper@unipv.it
License: GPLv3
Platform: UNKNOWN
Classifier: Programming Language :: Python :: 3
Classifier: Operating System :: OS Independent
License-File: LICENSE
Requires-Dist: setuptools
Requires-Dist: requests
Requires-Dist: packaging (>=19.0)
Requires-Dist: appdirs
Requires-Dist: errr
Requires-Dist: nrn-patch (>=3.0.0b0)
Provides-Extra: dev
Requires-Dist: sphinx ; extra == 'dev'
Requires-Dist: pre-commit ; extra == 'dev'
